README.txt
setup.py
aw/__init__.py
aw.managersmanager.egg-info/PKG-INFO
aw.managersmanager.egg-info/SOURCES.txt
aw.managersmanager.egg-info/dependency_links.txt
aw.managersmanager.egg-info/entry_points.txt
aw.managersmanager.egg-info/namespace_packages.txt
aw.managersmanager.egg-info/not-zip-safe
aw.managersmanager.egg-info/requires.txt
aw.managersmanager.egg-info/top_level.txt
aw/managersmanager/__init__.py
aw/managersmanager/configure.zcml
aw/managersmanager/console.py
aw/managersmanager/interfaces.py
aw/managersmanager/management.py
aw/managersmanager/version.txt
docs/HISTORY.txt