Metadata-Version: 1.0
Name: aw.managersmanager
Version: 1.0.0a1
Summary: Manages Plone site managers on multiple sites and clusters.
Home-page: http://pypi.python.org/pypi/aw.managersmanager
Author: Alter Way Solutions
Author-email: support@ingeniweb.com
License: GPL
Keywords: plone managers console
Platform: UNKNOWN
Classifier: Framework :: Plone
Classifier: Environment :: Console
Classifier: Programming Language :: Python
Classifier: Development Status :: 3 - Alpha
